TkEnhanced/__init__.py
TkEnhanced/components/__init__.py
TkEnhanced/components/enhanced_button.py
TkEnhanced/components/enhanced_checkbutton.py
TkEnhanced/components/enhanced_entry.py
TkEnhanced/components/enhanced_frame.py
TkEnhanced/components/enhanced_image.py
TkEnhanced/components/enhanced_label.py
TkEnhanced/components/enhanced_scrollable_frame.py
TkEnhanced/components/enhanced_sidebar.py
TkEnhanced/components/enhanced_tooltip.py
TkEnhanced/components/enhanced_widgets.py
TkEnhanced/components/enhanced_window.py
TkEnhanced/models/__init__.py
TkEnhanced/models/hover_misc.py
TkEnhanced/models/readable_misc.py
TkEnhanced/models/transparent_misc.py
TkEnhanced/utils/__init__.py
TkEnhanced/utils/color_utils.py
TkEnhanced/utils/constants.py
TkEnhanced/utils/types.py
TkEnhanced-2.2.2.dist-info/LICENSE
TkEnhanced-2.2.2.dist-info/METADATA
TkEnhanced-2.2.2.dist-info/WHEEL
TkEnhanced-2.2.2.dist-info/top_level.txt
TkEnhanced-2.2.2.dist-info/RECORD
