Metadata-Version: 2.1
Name: TkEnhanced
Version: 2.2.2
Summary: Enhanced Tkinter widgets for a modern look and additional functionality.
Author: Bunnitown
Classifier: Programming Language :: Python :: 3
Classifier: Programming Language :: Python :: 3.11
Classifier: License :: OSI Approved :: MIT License
Classifier: Operating System :: OS Independent
License-File: LICENSE
Requires-Dist: pillow>=10.4.0
Requires-Dist: numpy>=2.1.1
